{"version":"curated_v7_spanish","seed_id":"S0090","generation_stage":"COMPLETE","seed_pair":{"target":"If you can speak more slowly that would be great.","known":"Si puedes hablar más lentamente, eso sería excelente."},"recent_context":{"S0085":["no conozco a | esas personas | conozco a esas personas","I don't know | those people | know those people"],"S0086":["no fue posible | desafortunadamente","it wasn't possible | unfortunately"],"S0087":["son personas | que no conozco | personas que no conozco","they are people | that I don't know | people I don't know"],"S0088":["no estoy preparado | no estoy preparado para | para hablar con | personas que no conozco | todavía","I'm not ready | I'm not ready to | to talk to | people I don't know | yet"],"S0089":["pienso que | he hecho | he hecho mucho | en un breve tiempo | un breve tiempo","I think that | I've done | I've done a lot | in a short time | a short time"]},"legos":{"S0090L01":{"lego":["if you can","si puedes"],"type":"M","available_legos":427,"is_final_lego":false,"overlap_level":"none","target_phrase_count":10,"practice_phrases":[{"known":"Si puedes","target":"If you can"},{"known":"Si puedes ayudarme","target":"If you can help me"},{"known":"Si puedes hablar español","target":"If you can speak Spanish"},{"known":"Si puedes comenzar ahora","target":"If you can start now"},{"known":"Si puedes hablar más lentamente","target":"If you can speak more slowly"},{"known":"Si puedes esperarme un poco","target":"If you can wait for me a little"},{"known":"Si puedes ayudarme a comprender eso","target":"If you can help me understand that"},{"known":"No estoy seguro de si puedes hacer eso","target":"I'm not sure if you can do that"},{"known":"Si puedes venir mañana, eso sería bueno","target":"If you can come tomorrow, that would be good"},{"known":"Si puedes hablar con tu amigo sobre eso","target":"If you can talk to your friend about that"}],"phrase_distribution":{"short_1_to_2_legos":2,"medium_3_legos":2,"longer_4_legos":2,"longest_5_legos":4},"_metadata":{"lego_id":"S0090L01","seed_context":{"target":"If you can speak more slowly that would be great.","known":"Si puedes hablar más lentamente, eso sería excelente."},"components":[["si","if"],["puedes","you can"]]}},"S0090L02":{"lego":["speak more slowly","hablar más lentamente"],"type":"M","available_legos":428,"is_final_lego":false,"overlap_level":"none","target_phrase_count":10,"practice_phrases":[{"known":"Hablar más lentamente","target":"Speak more slowly"},{"known":"Habla más lentamente","target":"Speak more slowly"},{"known":"Puedes hablar más lentamente","target":"You can speak more slowly"},{"known":"Quiero hablar más lentamente","target":"I want to speak more slowly"},{"known":"Necesito hablar más lentamente en español","target":"I need to speak more slowly in Spanish"},{"known":"Voy a intentar hablar más lentamente","target":"I'm going to try to speak more slowly"},{"known":"Pienso que necesito hablar más lentamente con esas personas","target":"I think that I need to speak more slowly with those people"},{"known":"Es importante hablar más lentamente cuando estás aprendiendo","target":"It's important to speak more slowly when you're learning"},{"known":"No me gusta hablar más lentamente, pero es necesario","target":"I don't like speaking more slowly, but it's necessary"},{"known":"Si puedes hablar más lentamente, puedo comprender mejor","target":"If you can speak more slowly, I can understand better"}],"phrase_distribution":{"short_1_to_2_legos":2,"medium_3_legos":2,"longer_4_legos":2,"longest_5_legos":4},"_metadata":{"lego_id":"S0090L02","seed_context":{"target":"If you can speak more slowly that would be great.","known":"Si puedes hablar más lentamente, eso sería excelente."},"components":[["hablar","to speak"],["más","more"],["lentamente","slowly"]]}},"S0090L03":{"lego":["if you can speak","si puedes hablar"],"type":"M","available_legos":429,"is_final_lego":false,"overlap_level":"complete","target_phrase_count":5,"practice_phrases":[{"known":"Si puedes hablar español","target":"If you can speak Spanish"},{"known":"Si puedes hablar más lentamente","target":"If you can speak more slowly"},{"known":"Si puedes hablar conmigo mañana","target":"If you can speak with me tomorrow"},{"known":"Quiero saber si puedes hablar español","target":"I want to know if you can speak Spanish"},{"known":"Si puedes hablar con tu amigo sobre eso","target":"If you can speak with your friend about that"}],"phrase_distribution":{"longer_3_to_5_legos":5},"_metadata":{"lego_id":"S0090L03","seed_context":{"target":"If you can speak more slowly that would be great.","known":"Si puedes hablar más lentamente, eso sería excelente."},"components":[["si","if"],["puedes","you can"],["hablar","to speak"]]}},"S0090L04":{"lego":["that would be great","eso sería excelente"],"type":"M","available_legos":430,"is_final_lego":false,"overlap_level":"none","target_phrase_count":10,"practice_phrases":[{"known":"Eso sería excelente","target":"That would be great"},{"known":"Eso sería bueno","target":"That would be good"},{"known":"Eso sería muy bueno","target":"That would be very good"},{"known":"Pienso que eso sería excelente","target":"I think that would be great"},{"known":"Si puedes hacer eso, sería excelente","target":"If you can do that, it would be great"},{"known":"Eso sería excelente para mí","target":"That would be great for me"},{"known":"Si puedes ayudarme mañana, eso sería excelente","target":"If you can help me tomorrow, that would be great"},{"known":"Eso sería excelente si puedes hablar más lentamente","target":"That would be great if you can speak more slowly"},{"known":"Pienso que eso sería excelente para aprender español","target":"I think that would be great for learning Spanish"},{"known":"Si puedes venir a las seis, eso sería excelente","target":"If you can come at six, that would be great"}],"phrase_distribution":{"short_1_to_2_legos":2,"medium_3_legos":2,"longer_4_legos":2,"longest_5_legos":4},"_metadata":{"lego_id":"S0090L04","seed_context":{"target":"If you can speak more slowly that would be great.","known":"Si puedes hablar más lentamente, eso sería excelente."},"components":[["eso","that"],["sería","would be"],["excelente","excellent/great"]]}},"S0090L05":{"lego":["more slowly","más lentamente"],"type":"M","available_legos":431,"is_final_lego":true,"overlap_level":"complete","target_phrase_count":5,"practice_phrases":[{"known":"Más lentamente, por favor","target":"More slowly, please"},{"known":"Habla más lentamente","target":"Speak more slowly"},{"known":"Necesito hablar más lentamente","target":"I need to speak more slowly"},{"known":"Puedes hablar más lentamente, eso sería excelente","target":"You can speak more slowly, that would be great"},{"known":"Si puedes hablar más lentamente, eso sería excelente","target":"If you can speak more slowly, that would be great"}],"phrase_distribution":{"longer_3_to_5_legos":5},"_metadata":{"lego_id":"S0090L05","seed_context":{"target":"If you can speak more slowly that would be great.","known":"Si puedes hablar más lentamente, eso sería excelente."},"components":[["más","more"],["lentamente","slowly"]]}}},"_instructions":{"task":"Fill practice_phrases arrays using Phase 5 Ultimate Intelligence v5.0","methodology":"Read: docs/phase_intelligence/phase_5_lego_baskets.md (v5.0)","output":"Write to: public/vfs/courses/spa_for_eng/phase5_outputs/seed_s0090.json"},"_stats":{"new_legos_in_seed":5,"phrases_generated":40,"cumulative_legos_before":427}}
