{
  "S0394L01": {
    "lego": {
      "known": "that girl",
      "target": "esa niña"
    },
    "practice_phrases": [
      {
        "known": "that girl",
        "target": "esa niña"
      },
      {
        "known": "that girl over there",
        "target": "esa niña de ahí"
      },
      {
        "known": "that girl is walking",
        "target": "esa niña está caminando"
      },
      {
        "known": "that girl with the yellow dress",
        "target": "esa niña con el vestido amarillo"
      },
      {
        "known": "I know that girl",
        "target": "conozco a esa niña"
      },
      {
        "known": "do you know that girl?",
        "target": "¿conoces a esa niña?"
      },
      {
        "known": "that girl is my friend",
        "target": "esa niña es mi amiga"
      },
      {
        "known": "that girl works here",
        "target": "esa niña trabaja aquí"
      },
      {
        "known": "I saw that girl near the entrance",
        "target": "vi a esa niña cerca de la entrada"
      },
      {
        "known": "that girl who is standing there",
        "target": "esa niña que está de pie ahí"
      }
    ],
    "is_final_lego": false,
    "phrase_count": 10
  },
  "S0394L02": {
    "lego": {
      "known": "with the yellow dress",
      "target": "con el vestido amarillo"
    },
    "practice_phrases": [
      {
        "known": "with the yellow dress",
        "target": "con el vestido amarillo"
      },
      {
        "known": "the girl with the yellow dress",
        "target": "la niña con el vestido amarillo"
      },
      {
        "known": "that girl with the yellow dress",
        "target": "esa niña con el vestido amarillo"
      },
      {
        "known": "the person with the yellow dress",
        "target": "la persona con el vestido amarillo"
      },
      {
        "known": "the one with the yellow dress",
        "target": "la que tiene el vestido amarillo"
      },
      {
        "known": "the child with the yellow dress",
        "target": "la niña con el vestido amarillo"
      },
      {
        "known": "I know the one with the yellow dress",
        "target": "conozco a la que tiene el vestido amarillo"
      },
      {
        "known": "that person with the yellow dress is my friend",
        "target": "esa persona con el vestido amarillo es mi amiga"
      },
      {
        "known": "the girl with the yellow dress is walking",
        "target": "la niña con el vestido amarillo está caminando"
      },
      {
        "known": "do you see the one with the yellow dress?",
        "target": "¿ves a la que tiene el vestido amarillo?"
      }
    ],
    "is_final_lego": false,
    "phrase_count": 10
  },
  "S0394L03": {
    "lego": {
      "known": "the yellow dress",
      "target": "el vestido amarillo"
    },
    "practice_phrases": [
      {
        "known": "the yellow dress",
        "target": "el vestido amarillo"
      },
      {
        "known": "with the yellow dress",
        "target": "con el vestido amarillo"
      },
      {
        "known": "I like the yellow dress",
        "target": "me gusta el vestido amarillo"
      },
      {
        "known": "the girl with the yellow dress",
        "target": "la niña con el vestido amarillo"
      },
      {
        "known": "the one with the yellow dress",
        "target": "la que tiene el vestido amarillo"
      },
      {
        "known": "I want the yellow dress",
        "target": "quiero el vestido amarillo"
      },
      {
        "known": "she has the yellow dress",
        "target": "tiene el vestido amarillo"
      },
      {
        "known": "the yellow dress is beautiful",
        "target": "el vestido amarillo es hermoso"
      },
      {
        "known": "I saw the one with the yellow dress",
        "target": "vi a la que tiene el vestido amarillo"
      },
      {
        "known": "where did you buy the yellow dress?",
        "target": "¿dónde compraste el vestido amarillo?"
      },
      {
        "known": "That girl with the yellow dress.",
        "target": "Esa niña con el vestido amarillo."
      }
    ],
    "is_final_lego": true,
    "phrase_count": 11
  }
}
