{
  "S0507L01": {
    "lego": ["we moved to", "我们搬到了"],
    "type": "M",
    "is_final_lego": false,
    "current_seed_legos_available": [],
    "practice_phrases": [
      ["We moved to.", "我们搬到了。", null, 1],
      ["Maybe we moved to.", "也许我们搬到了。", null, 2],
      ["Years ago we moved to.", "多年前我们搬到了。", null, 2],
      ["We moved to the entrance.", "我们搬到了入口。", null, 3],
      ["Maybe we moved to the entrance.", "也许我们搬到了入口。", null, 3],
      ["Years ago we moved to the entrance.", "多年前我们搬到了入口。", null, 3],
      ["We moved to inside the entrance.", "我们搬到了入口里面。", null, 4],
      ["Maybe years ago we moved to the entrance.", "也许多年前我们搬到了入口。", null, 4],
      ["Before we moved we moved to the entrance.", "我们搬家之前我们搬到了入口。", null, 5],
      ["Years ago before we moved we moved to around here.", "多年前我们搬家之前我们搬到了在这附近。", null, 6]
    ],
    "phrase_distribution": {
      "short_1_to_2_legos": 2,
      "medium_3_legos": 2,
      "longer_4_legos": 2,
      "longest_5_legos": 4
    },
    "target_phrase_count": 10
  },
  "S0507L03": {
    "lego": ["moved to the city", "搬到了城市"],
    "type": "M",
    "is_final_lego": true,
    "current_seed_legos_available": [["we moved to", "我们搬到了"]],
    "practice_phrases": [
      ["Moved to the city.", "搬到了城市。", null, 1],
      ["We moved to the city.", "我们搬到了城市。", null, 2],
      ["Maybe moved to the city.", "也许搬到了城市。", null, 2],
      ["Maybe we moved to the city.", "也许我们搬到了城市。", null, 3],
      ["Years ago moved to the city.", "多年前搬到了城市。", null, 3],
      ["Years ago we moved to the city.", "多年前我们搬到了城市。", null, 3],
      ["Maybe years ago we moved to the city.", "也许多年前我们搬到了城市。", null, 4],
      ["Before we moved we moved to the city.", "我们搬家之前我们搬到了城市。", null, 5],
      ["Years ago before we moved we moved to the city.", "多年前我们搬家之前我们搬到了城市。", null, 6],
      ["We moved to the city.", "我们搬到了城市。", null, 2]
    ],
    "phrase_distribution": {
      "short_1_to_2_legos": 2,
      "medium_3_legos": 2,
      "longer_4_legos": 2,
      "longest_5_legos": 4
    },
    "target_phrase_count": 10
  }
}
