{
  "S0026L01": {
    "lego": ["我喜欢", "I like"],
    "e": [
      "我喜欢感觉好像我快准备好走了",
      "我喜欢跟你现在说中文",
      "我喜欢试着学怎么说",
      "我喜欢尽量常说中文",
      "我喜欢今天跟别人练习说",
      "我喜欢现在跟你说中文",
      "我喜欢今天学一个词",
      "我喜欢试着想起一个词",
      "我喜欢明天跟你一起练习",
      "我喜欢说得很好中文"
    ],
    "d": {
      "我喜欢感觉好像我快准备好走了": "I like feeling as if I'm nearly ready to go",
      "我喜欢跟你现在说中文": "I like speaking Chinese with you now",
      "我喜欢试着学怎么说": "I like trying to learn how to speak",
      "我喜欢尽量常说中文": "I like speaking Chinese as often as possible",
      "我喜欢今天跟别人练习说": "I like practicing speaking with someone else today",
      "我喜欢现在跟你说中文": "I like speaking Chinese with you now",
      "我喜欢今天学一个词": "I like learning a word today",
      "我喜欢试着想起一个词": "I like trying to remember a word",
      "我喜欢明天跟你一起练习": "I like practicing with you tomorrow",
      "我喜欢说得很好中文": "I like speaking Chinese very well"
    }
  },
  "S0026L02": {
    "lego": ["感觉", "feeling"],
    "e": [
      "我喜欢感觉好像我快准备好走了",
      "我想感觉准备好说中文",
      "我要感觉很好今天",
      "感觉好像我在试着学",
      "我喜欢感觉我会说中文",
      "感觉我快要学会说了",
      "我想感觉准备好跟你说",
      "感觉好像我在试着学怎么说",
      "我喜欢感觉很好明天",
      "感觉我要跟你一起练习"
    ],
    "d": {
      "我喜欢感觉好像我快准备好走了": "I like feeling as if I'm nearly ready to go",
      "我想感觉准备好说中文": "I want to feel ready to speak Chinese",
      "我要感觉很好今天": "I'm going to feel very well today",
      "感觉好像我在试着学": "Feeling as if I'm trying to learn",
      "我喜欢感觉我会说中文": "I like feeling I speak Chinese",
      "感觉我快要学会说了": "Feeling I'm going to learn to speak soon",
      "我想感觉准备好跟你说": "I want to feel ready to speak with you",
      "感觉好像我在试着学怎么说": "Feeling as if I'm trying to learn how to speak",
      "我喜欢感觉很好明天": "I like feeling very well tomorrow",
      "感觉我要跟你一起练习": "Feeling I'm going to practice with you"
    }
  },
  "S0026L03": {
    "lego": ["好像", "as if"],
    "e": [
      "我喜欢感觉好像我快准备好走了",
      "好像我在试着学中文",
      "好像我会说中文很好",
      "好像我想跟你现在说",
      "好像我在学一个词今天",
      "好像我要跟你练习说",
      "好像我现在说得很好中文",
      "好像我在试着想起一个词",
      "好像我跟你一起学中文",
      "好像我快要准备好说了"
    ],
    "d": {
      "我喜欢感觉好像我快准备好走了": "I like feeling as if I'm nearly ready to go",
      "好像我在试着学中文": "As if I'm trying to learn Chinese",
      "好像我会说中文很好": "As if I speak Chinese very well",
      "好像我想跟你现在说": "As if I want to speak with you now",
      "好像我在学一个词今天": "As if I'm learning a word today",
      "好像我要跟你练习说": "As if I'm going to practice speaking with you",
      "好像我现在说得很好中文": "As if I speak Chinese very well now",
      "好像我在试着想起一个词": "As if I'm trying to remember a word",
      "好像我跟你一起学中文": "As if I'm learning Chinese with you",
      "好像我快要准备好说了": "As if I'm nearly ready to speak"
    }
  },
  "S0026L04": {
    "lego": ["快", "nearly"],
    "e": [
      "我喜欢感觉好像我快准备好走了",
      "我快准备好说中文了",
      "我快要学会说中文了",
      "我快要跟你说中文了",
      "快准备好今天练习说了",
      "我快要想起一个词了",
      "快要说得很好中文了",
      "我快准备好现在试着说了",
      "快要跟别人说中文了",
      "我快要会说中文很好了"
    ],
    "d": {
      "我喜欢感觉好像我快准备好走了": "I like feeling as if I'm nearly ready to go",
      "我快准备好说中文了": "I'm nearly ready to speak Chinese",
      "我快要学会说中文了": "I'm nearly going to learn to speak Chinese",
      "我快要跟你说中文了": "I'm nearly going to speak Chinese with you",
      "快准备好今天练习说了": "Nearly ready to practice speaking today",
      "我快要想起一个词了": "I'm nearly going to remember a word",
      "快要说得很好中文了": "Nearly speaking Chinese very well",
      "我快准备好现在试着说了": "I'm nearly ready to try to speak now",
      "快要跟别人说中文了": "Nearly going to speak Chinese with someone else",
      "我快要会说中文很好了": "I'm nearly going to speak Chinese very well"
    }
  },
  "S0026L05": {
    "lego": ["准备好", "ready"],
    "e": [
      "我喜欢感觉好像我快准备好走了",
      "我准备好现在说中文",
      "我想准备好今天学中文",
      "准备好跟你一起练习说",
      "我要准备好试着说中文",
      "我快准备好跟你说了",
      "准备好现在跟别人说",
      "我想准备好明天说中文",
      "准备好跟别人一起练习说",
      "我准备好今天学一个词"
    ],
    "d": {
      "我喜欢感觉好像我快准备好走了": "I like feeling as if I'm nearly ready to go",
      "我准备好现在说中文": "I'm ready to speak Chinese now",
      "我想准备好今天学中文": "I want to be ready to learn Chinese today",
      "准备好跟你一起练习说": "Ready to practice speaking with you",
      "我要准备好试着说中文": "I'm going to be ready to try to speak Chinese",
      "我快准备好跟你说了": "I'm nearly ready to speak with you",
      "准备好现在跟别人说": "Ready to speak with someone else now",
      "我想准备好明天说中文": "I want to be ready to speak Chinese tomorrow",
      "准备好跟别人一起练习说": "Ready to practice speaking with someone else",
      "我准备好今天学一个词": "I'm ready to learn a word today"
    }
  },
  "S0026L06": {
    "lego": ["走了", "to go"],
    "e": [
      "我喜欢感觉好像我快准备好走了",
      "我想现在准备好走了",
      "我要明天跟你一起走了",
      "准备好今天跟别人走了",
      "我快要跟你一起走了",
      "我想今天准备好走了",
      "准备好跟你一起快点儿走了",
      "我要跟别人明天走了",
      "我想快点儿准备好走了",
      "我快准备好现在走了"
    ],
    "d": {
      "我喜欢感觉好像我快准备好走了": "I like feeling as if I'm nearly ready to go",
      "我想现在准备好走了": "I want to be ready to go now",
      "我要明天跟你一起走了": "I'm going to go with you tomorrow",
      "准备好今天跟别人走了": "Ready to go with someone else today",
      "我快要跟你一起走了": "I'm nearly going to go with you",
      "我想今天准备好走了": "I want to be ready to go today",
      "准备好跟你一起快点儿走了": "Ready to go quickly with you",
      "我要跟别人明天走了": "I'm going to go with someone else tomorrow",
      "我想快点儿准备好走了": "I want to be ready to go quickly",
      "我快准备好现在走了": "I'm nearly ready to go now"
    }
  },
  "S0027L01": {
    "lego": ["我不喜欢", "I don't like"],
    "e": [
      "我不喜欢花太多时间回答",
      "我不喜欢整天说中文",
      "我不喜欢猜怎么说什么",
      "我不喜欢现在停止说中文",
      "我不喜欢整天跟别人说",
      "我不喜欢快点儿学会说",
      "我不喜欢现在试着学中文",
      "我不喜欢跟别人一起练习说",
      "我不喜欢试着想起一个词",
      "我不喜欢今天学怎么说"
    ],
    "d": {
      "我不喜欢花太多时间回答": "I don't like taking too much time to answer",
      "我不喜欢整天说中文": "I don't like speaking Chinese all day",
      "我不喜欢猜怎么说什么": "I don't like guessing how to say something",
      "我不喜欢现在停止说中文": "I don't like stopping talking Chinese now",
      "我不喜欢整天跟别人说": "I don't like speaking with someone else all day",
      "我不喜欢快点儿学会说": "I don't like learning to speak quickly",
      "我不喜欢现在试着学中文": "I don't like trying to learn Chinese now",
      "我不喜欢跟别人一起练习说": "I don't like practicing speaking with someone else",
      "我不喜欢试着想起一个词": "I don't like trying to remember a word",
      "我不喜欢今天学怎么说": "I don't like learning how to speak today"
    }
  },
  "S0027L02": {
    "lego": ["花", "taking"],
    "e": [
      "我不喜欢花太多时间回答",
      "我想花时间试着学中文",
      "我要花时间试着说中文",
      "花时间跟你练习说",
      "我在花时间学怎么说中文",
      "我喜欢花时间跟你说中文",
      "花时间试着想起一个词",
      "我想花时间今天学中文",
      "花时间现在跟别人说",
      "我不想花太多时间学"
    ],
    "d": {
      "我不喜欢花太多时间回答": "I don't like taking too much time to answer",
      "我想花时间试着学中文": "I want to take time to try to learn Chinese",
      "我要花时间试着说中文": "I'm going to take time to try to speak Chinese",
      "花时间跟你练习说": "Taking time to practice speaking with you",
      "我在花时间学怎么说中文": "I'm taking time learning how to speak Chinese",
      "我喜欢花时间跟你说中文": "I like taking time to speak Chinese with you",
      "花时间试着想起一个词": "Taking time to try to remember a word",
      "我想花时间今天学中文": "I want to take time to learn Chinese today",
      "花时间现在跟别人说": "Taking time to speak with someone else now",
      "我不想花太多时间学": "I don't want to take too much time learning"
    }
  },
  "S0027L03": {
    "lego": ["太多时间", "too much time"],
    "e": [
      "我不喜欢花太多时间回答",
      "我在花太多时间学中文",
      "不想花太多时间说中文",
      "花太多时间试着想起一个词",
      "我不喜欢花太多时间说",
      "花太多时间跟你练习说",
      "我要花太多时间学怎么说中文",
      "不喜欢花太多时间跟你说中文",
      "花太多时间现在试着学",
      "我花太多时间今天学中文"
    ],
    "d": {
      "我不喜欢花太多时间回答": "I don't like taking too much time to answer",
      "我在花太多时间学中文": "I'm taking too much time learning Chinese",
      "不想花太多时间说中文": "Don't want to take too much time speaking Chinese",
      "花太多时间试着想起一个词": "Taking too much time trying to remember a word",
      "我不喜欢花太多时间说": "I don't like taking too much time speaking",
      "花太多时间跟你练习说": "Taking too much time practicing speaking with you",
      "我要花太多时间学怎么说中文": "I'm going to take too much time learning how to speak Chinese",
      "不喜欢花太多时间跟你说中文": "Don't like taking too much time speaking Chinese with you",
      "花太多时间现在试着学": "Taking too much time trying to learn now",
      "我花太多时间今天学中文": "I'm taking too much time learning Chinese today"
    }
  },
  "S0027L04": {
    "lego": ["回答", "to answer"],
    "e": [
      "我不喜欢花太多时间回答",
      "我想现在快点儿回答",
      "我要试着用中文回答",
      "我在试着学怎么回答",
      "我想现在准备好回答",
      "回答怎么用中文说什么",
      "我要明天跟你一起回答",
      "我喜欢快点儿准备好回答",
      "我想明天准备好回答",
      "准备好跟你一起回答"
    ],
    "d": {
      "我不喜欢花太多时间回答": "I don't like taking too much time to answer",
      "我想现在快点儿回答": "I want to answer quickly now",
      "我要试着用中文回答": "I'm going to try to answer in Chinese",
      "我在试着学怎么回答": "I'm trying to learn how to answer",
      "我想现在准备好回答": "I want to be ready to answer now",
      "回答怎么用中文说什么": "To answer how to say something in Chinese",
      "我要明天跟你一起回答": "I'm going to answer with you tomorrow",
      "我喜欢快点儿准备好回答": "I like being ready to answer quickly",
      "我想明天准备好回答": "I want to be ready to answer tomorrow",
      "准备好跟你一起回答": "Ready to answer with you"
    }
  },
  "S0028L01": {
    "lego": ["一有机会就", "as soon as you can"],
    "e": [
      "一有机会就开始说是有用的",
      "我想一有机会就说中文",
      "我要一有机会就学中文",
      "一有机会就跟你练习说",
      "我一有机会就试着说中文",
      "一有机会就跟你说中文很好",
      "我一有机会就学会说",
      "一有机会就说得很好中文",
      "我想一有机会就试着学",
      "一有机会就准备好说中文"
    ],
    "d": {
      "一有机会就开始说是有用的": "It's useful to start talking as soon as you can",
      "我想一有机会就说中文": "I want to speak Chinese as soon as I can",
      "我要一有机会就学中文": "I'm going to learn Chinese as soon as I can",
      "一有机会就跟你练习说": "To practice speaking with you as soon as you can",
      "我一有机会就试着说中文": "I try to speak Chinese as soon as I can",
      "一有机会就跟你说中文很好": "To speak Chinese very well with you as soon as you can",
      "我一有机会就学会说": "I learn to speak as soon as I can",
      "一有机会就说得很好中文": "To speak Chinese very well as soon as you can",
      "我想一有机会就试着学": "I want to try to learn as soon as I can",
      "一有机会就准备好说中文": "To be ready to speak Chinese as soon as you can"
    }
  },
  "S0028L02": {
    "lego": ["开始说", "to start talking"],
    "e": [
      "一有机会就开始说是有用的",
      "我想今天开始说中文",
      "我要跟你一起开始说",
      "我快要准备好开始说了",
      "开始说现在跟别人中文",
      "我喜欢明天开始说中文",
      "我想明天跟你开始说",
      "开始说跟你一起学中文",
      "我要今天准备好开始说",
      "准备好现在跟你开始说"
    ],
    "d": {
      "一有机会就开始说是有用的": "It's useful to start talking as soon as you can",
      "我想今天开始说中文": "I want to start talking Chinese today",
      "我要跟你一起开始说": "I'm going to start talking with you",
      "我快要准备好开始说了": "I'm nearly ready to start talking",
      "开始说现在跟别人中文": "To start talking Chinese with someone else now",
      "我喜欢明天开始说中文": "I like starting to talk Chinese tomorrow",
      "我想明天跟你开始说": "I want to start talking with you tomorrow",
      "开始说跟你一起学中文": "To start talking learning Chinese with you",
      "我要今天准备好开始说": "I'm going to be ready to start talking today",
      "准备好现在跟你开始说": "Ready to start talking with you now"
    }
  },
  "S0028L03": {
    "lego": ["是有用的", "It's useful"],
    "e": [
      "一有机会就开始说是有用的",
      "跟你一起学中文是有用的",
      "试着说中文现在是有用的",
      "跟别人练习说是有用的",
      "跟你说中文今天是有用的",
      "现在学怎么说是有用的",
      "试着想起一个词是有用的",
      "尽量常说中文是有用的",
      "跟别人一起练习说是有用的",
      "快点儿学会说是有用的"
    ],
    "d": {
      "一有机会就开始说是有用的": "It's useful to start talking as soon as you can",
      "跟你一起学中文是有用的": "It's useful to learn Chinese with you",
      "试着说中文现在是有用的": "It's useful to try to speak Chinese now",
      "跟别人练习说是有用的": "It's useful to practice speaking with someone else",
      "跟你说中文今天是有用的": "It's useful to speak Chinese with you today",
      "现在学怎么说是有用的": "It's useful to learn how to speak now",
      "试着想起一个词是有用的": "It's useful to try to remember a word",
      "尽量常说中文是有用的": "It's useful to speak Chinese as often as possible",
      "跟别人一起练习说是有用的": "It's useful to practice speaking with someone else",
      "快点儿学会说是有用的": "It's useful to learn to speak quickly"
    }
  },
  "S0029L01": {
    "lego": ["我期待", "I'm looking forward to"],
    "e": [
      "我期待一有机会就说得更好",
      "我期待今天学怎么说中文",
      "我期待明天跟你说中文",
      "我期待明天准备好说中文",
      "我期待试着学会说中文",
      "我期待现在开始说中文",
      "我期待跟别人一起练习说",
      "我期待今天学一个词",
      "我期待明天准备好学",
      "我期待跟别人说中文"
    ],
    "d": {
      "我期待一有机会就说得更好": "I'm looking forward to speaking better as soon as I can",
      "我期待今天学怎么说中文": "I'm looking forward to learning how to speak Chinese today",
      "我期待明天跟你说中文": "I'm looking forward to speaking Chinese with you tomorrow",
      "我期待明天准备好说中文": "I'm looking forward to being ready to speak Chinese tomorrow",
      "我期待试着学会说中文": "I'm looking forward to trying to learn to speak Chinese",
      "我期待现在开始说中文": "I'm looking forward to starting to speak Chinese now",
      "我期待跟别人一起练习说": "I'm looking forward to practicing speaking with someone else",
      "我期待今天学一个词": "I'm looking forward to learning a word today",
      "我期待明天准备好学": "I'm looking forward to being ready to learn tomorrow",
      "我期待跟别人说中文": "I'm looking forward to speaking Chinese with someone else"
    }
  },
  "S0029L02": {
    "lego": ["说得更好", "speaking better"],
    "e": [
      "我期待一有机会就说得更好",
      "我想明天说得更好中文",
      "我要跟你说得更好",
      "我在试着说得更好中文",
      "我喜欢现在说得更好",
      "说得更好现在跟你中文",
      "我快要准备好说得更好了",
      "说得更好明天跟别人",
      "我想跟你一起说得更好",
      "说得更好今天学中文"
    ],
    "d": {
      "我期待一有机会就说得更好": "I'm looking forward to speaking better as soon as I can",
      "我想明天说得更好中文": "I want to speak Chinese better tomorrow",
      "我要跟你说得更好": "I'm going to speak better with you",
      "我在试着说得更好中文": "I'm trying to speak Chinese better",
      "我喜欢现在说得更好": "I like speaking better now",
      "说得更好现在跟你中文": "Speaking Chinese better with you now",
      "我快要准备好说得更好了": "I'm nearly ready to speak better",
      "说得更好明天跟别人": "Speaking better with someone else tomorrow",
      "我想跟你一起说得更好": "I want to speak better with you",
      "说得更好今天学中文": "Speaking Chinese better learning today"
    }
  },
  "S0030L01": {
    "lego": ["我想", "I wanted"],
    "e": [
      "我昨天想问你一些事",
      "我想跟你说中文现在",
      "我想今天学怎么说",
      "我想现在试着说中文",
      "我想明天试着学",
      "我想准备好说中文",
      "我想明天学一个词",
      "我想跟别人一起练习说",
      "我想今天说得很好",
      "我想快点儿学会说"
    ],
    "d": {
      "我昨天想问你一些事": "I wanted to ask you something yesterday",
      "我想跟你说中文现在": "I wanted to speak Chinese with you now",
      "我想今天学怎么说": "I wanted to learn how to speak today",
      "我想现在试着说中文": "I wanted to try to speak Chinese now",
      "我想明天试着学": "I wanted to try to learn tomorrow",
      "我想准备好说中文": "I wanted to be ready to speak Chinese",
      "我想明天学一个词": "I wanted to learn a word tomorrow",
      "我想跟别人一起练习说": "I wanted to practice speaking with someone else",
      "我想今天说得很好": "I wanted to speak very well today",
      "我想快点儿学会说": "I wanted to learn to speak quickly"
    }
  },
  "S0030L02": {
    "lego": ["昨天", "yesterday"],
    "e": [
      "我昨天想问你一些事",
      "我昨天跟你说中文",
      "我昨天试着学怎么说",
      "我昨天试着说中文",
      "我昨天跟你一起练习说",
      "我昨天想学会说中文",
      "昨天我说得很好中文",
      "我昨天跟别人说中文",
      "我昨天准备好说了",
      "我昨天在学怎么说中文"
    ],
    "d": {
      "我昨天想问你一些事": "I wanted to ask you something yesterday",
      "我昨天跟你说中文": "I spoke Chinese with you yesterday",
      "我昨天试着学怎么说": "I tried to learn how to speak yesterday",
      "我昨天试着说中文": "I tried to speak Chinese yesterday",
      "我昨天跟你一起练习说": "I practiced speaking with you yesterday",
      "我昨天想学会说中文": "I wanted to learn to speak Chinese yesterday",
      "昨天我说得很好中文": "I spoke Chinese very well yesterday",
      "我昨天跟别人说中文": "I spoke Chinese with someone else yesterday",
      "我昨天准备好说了": "I was ready to speak yesterday",
      "我昨天在学怎么说中文": "I was learning how to speak Chinese yesterday"
    }
  },
  "S0030L03": {
    "lego": ["问你", "to ask you"],
    "e": [
      "我昨天想问你一些事",
      "我想现在问你怎么说",
      "我要问你怎么用中文说",
      "我想现在准备好问你",
      "问你明天怎么说中文",
      "我喜欢跟你一起问你",
      "我要问你一个词怎么说",
      "想今天快点儿问你",
      "我在试着学怎么问你",
      "准备好跟你一起问你"
    ],
    "d": {
      "我昨天想问你一些事": "I wanted to ask you something yesterday",
      "我想现在问你怎么说": "I want to ask you how to speak now",
      "我要问你怎么用中文说": "I'm going to ask you how to say in Chinese",
      "我想现在准备好问你": "I want to be ready to ask you now",
      "问你明天怎么说中文": "To ask you how to speak Chinese tomorrow",
      "我喜欢跟你一起问你": "I like asking you with you",
      "我要问你一个词怎么说": "I'm going to ask you how to say a word",
      "想今天快点儿问你": "Want to ask you quickly today",
      "我在试着学怎么问你": "I'm trying to learn how to ask you",
      "准备好跟你一起问你": "Ready to ask you with you"
    }
  },
  "S0030L04": {
    "lego": ["一些事", "something"],
    "e": [
      "我昨天想问你一些事",
      "我想用中文说一些事",
      "我要今天学一些事",
      "一些事怎么用中文说",
      "我在试着想起一些事今天",
      "我想跟你说一些事中文",
      "说一些事用中文怎么说",
      "我要试着解释一些事",
      "想今天学会一些事",
      "我喜欢跟你说一些事"
    ],
    "d": {
      "我昨天想问你一些事": "I wanted to ask you something yesterday",
      "我想用中文说一些事": "I want to say something in Chinese",
      "我要今天学一些事": "I'm going to learn something today",
      "一些事怎么用中文说": "How to say something in Chinese",
      "我在试着想起一些事今天": "I'm trying to remember something today",
      "我想跟你说一些事中文": "I want to speak something Chinese with you",
      "说一些事用中文怎么说": "To say something how to say in Chinese",
      "我要试着解释一些事": "I'm going to try to explain something",
      "想今天学会一些事": "Want to learn something today",
      "我喜欢跟你说一些事": "I like saying something with you"
    }
  }
}
