{
  "uuid": "ae703d03790e49b65356d4333554527e",
  "type": "lego_deduplicated",
  "text": "are you",
  "provenance": [
    {
      "provenance": "S24L3",
      "source_translation_uuid": "4340624e8478e3216d90b7f5740daa6c",
      "source_seed_id": "S024",
      "original_uuid": "8d416aab193e87bd193ec3a438c44b3c"
    },
    {
      "provenance": "S3L3",
      "source_translation_uuid": "c91ce9bcda96a854c211857e1675e88e",
      "source_seed_id": "S003",
      "original_uuid": "54b995bb27a9f03294bd863bad156969"
    }
  ],
  "fcfs_score": 18.4,
  "utility_score": 42,
  "pedagogical_score": 40,
  "metadata": {
    "course_code": "spa_for_eng_30seeds",
    "phase": "phase_4",
    "duplicate_count": 2,
    "canonical_provenance": "S24L3",
    "all_sources": "S24L3, S3L3",
    "created_at": "2025-10-10T11:13:33.061Z"
  }
}
